img2cmd.py
img2cmd-1.0.0.dist-info/WHEEL
img2cmd-1.0.0.dist-info/METADATA
img2cmd-1.0.0.dist-info/RECORD
